gopro_overlay/__init__.py
gopro_overlay/__version__.py
gopro_overlay/arguments.py
gopro_overlay/assertion.py
gopro_overlay/buffering.py
gopro_overlay/common.py
gopro_overlay/config.py
gopro_overlay/counter.py
gopro_overlay/date_overlap.py
gopro_overlay/dimensions.py
gopro_overlay/entry.py
gopro_overlay/exceptions.py
gopro_overlay/execution.py
gopro_overlay/fake.py
gopro_overlay/ffmpeg.py
gopro_overlay/ffmpeg_gopro.py
gopro_overlay/ffmpeg_overlay.py
gopro_overlay/ffmpeg_profile.py
gopro_overlay/filenaming.py
gopro_overlay/fit.py
gopro_overlay/font.py
gopro_overlay/framemeta.py
gopro_overlay/framemeta_gpmd.py
gopro_overlay/framemeta_gpx.py
gopro_overlay/functional.py
gopro_overlay/geo.py
gopro_overlay/geo_render.py
gopro_overlay/geocode.py
gopro_overlay/gpmd_filters.py
gopro_overlay/gpx.py
gopro_overlay/journey.py
gopro_overlay/layout.py
gopro_overlay/layout_components.py
gopro_overlay/layout_xml.py
gopro_overlay/layout_xml_attribute.py
gopro_overlay/layout_xml_cairo.py
gopro_overlay/loading.py
gopro_overlay/log.py
gopro_overlay/models.py
gopro_overlay/parsing.py
gopro_overlay/point.py
gopro_overlay/privacy.py
gopro_overlay/process.py
gopro_overlay/progress_frames.py
gopro_overlay/progresstrack.py
gopro_overlay/rdp.py
gopro_overlay/smoothing.py
gopro_overlay/timeseries.py
gopro_overlay/timeseries_process.py
gopro_overlay/timeunits.py
gopro_overlay/timing.py
gopro_overlay/units.py
gopro_overlay/gpmf/__init__.py
gopro_overlay/gpmf/calc.py
gopro_overlay/gpmf/gpmf.py
gopro_overlay/gpmf/visitors/__init__.py
gopro_overlay/gpmf/visitors/cori.py
gopro_overlay/gpmf/visitors/debug.py
gopro_overlay/gpmf/visitors/find.py
gopro_overlay/gpmf/visitors/gps.py
gopro_overlay/gpmf/visitors/grav.py
gopro_overlay/gpmf/visitors/xyz.py
gopro_overlay/icons/__init__.py
gopro_overlay/icons/bicycle.png
gopro_overlay/icons/car.png
gopro_overlay/icons/faq.png
gopro_overlay/icons/forbidden.png
gopro_overlay/icons/gauge-1.png
gopro_overlay/icons/gauge.png
gopro_overlay/icons/gps_lock_2d.png
gopro_overlay-0.129.0.dist-info/licenses/LICENSE.md
gopro_overlay-0.129.0.dist-info/METADATA
gopro_overlay-0.129.0.dist-info/WHEEL
gopro_overlay-0.129.0.dist-info/top_level.txt
gopro_overlay-0.129.0.dist-info/RECORD
