Metadata-Version: 2.4
Name: gopro-overlay
Version: 0.129.0
Summary: Overlay graphics dashboards onto GoPro footage, or create videos from GPX or FIT files
Author-email: James Richardson <james+gopro@time4tea.net>
License: MIT
Project-URL: Homepage, https://github.com/time4tea/gopro-dashboard-overlay
Project-URL: Source, https://github.com/time4tea/gopro-dashboard-overlay
Classifier: Development Status :: 5 - Production/Stable
Classifier: License :: OSI Approved :: GNU General Public License v3 or later (GPLv3+)
Classifier: Programming Language :: Python :: 3.14
Classifier: Programming Language :: Python :: 3.13
Classifier: Programming Language :: Python :: 3.12
Classifier: Programming Language :: Python :: 3.11
Classifier: Environment :: Console
Classifier: Topic :: Multimedia :: Graphics
Classifier: Topic :: Multimedia :: Video
Requires-Python: >=3.11
License-File: LICENSE.md
Requires-Dist: pillow==11.3.0
Requires-Dist: pint==0.25.1
Requires-Dist: geotiler==0.15
Requires-Dist: gpxpy==1.6.1
Requires-Dist: fitdecode==0.10.0
Requires-Dist: geographiclib==1.52
Requires-Dist: progressbar2==4.2.0
Requires-Dist: requests==2.32.5
Requires-Dist: sqlitedict==2.1.0
Provides-Extra: cairo
Requires-Dist: pycairo==1.28.0; extra == "cairo"
Provides-Extra: test
Requires-Dist: gopro-overlay[cairo]; extra == "test"
Requires-Dist: pytest; extra == "test"
Provides-Extra: dev
Requires-Dist: gopro-overlay[test]; extra == "dev"
Requires-Dist: black; extra == "dev"
Requires-Dist: viztracer; extra == "dev"
Requires-Dist: bump-my-version; extra == "dev"
Dynamic: license-file
